irclm/__init__.py
irclm/irclm.py
irclm-0.0.2.dist-info/entry_points.txt
irclm-0.0.2.dist-info/WHEEL
irclm-0.0.2.dist-info/METADATA
irclm-0.0.2.dist-info/RECORD
