Metadata-Version: 2.1
Name: irclm
Version: 0.0.2
Summary: 
Author: Brett Holman
Author-email: bholman.devel@gmail.com
Requires-Python: >=3.7.2,<4.0.0
Classifier: Programming Language :: Python :: 3
Classifier: Programming Language :: Python :: 3.8
Classifier: Programming Language :: Python :: 3.9
Classifier: Programming Language :: Python :: 3.10
Requires-Dist: aiohttp (>=3.8.3,<4.0.0)
Requires-Dist: black (>=22.8.0,<23.0.0)
Requires-Dist: flake8 (>=5.0.4,<6.0.0)
Requires-Dist: isort (>=5.10.1,<6.0.0)
Requires-Dist: pylint (>=2.15.3,<3.0.0)
Requires-Dist: toml (>=0.10.2,<0.11.0)
